parse_2d/__init__.py
parse_2d/diagram.py
parse_2d/regions.py
parse_2d/tokens/__init__.py
parse_2d/tokens/box_tokenizer.py
parse_2d/tokens/template_tokenizer.py
parse_2d/tokens/tiny_tokenizer.py
parse_2d/tokens/translation.py
parse_2d/tokens/types.py
parse_2d/tokens/wire_tokenizer.py
parse_2d-1.0.0.dist-info/LICENSE
parse_2d-1.0.0.dist-info/METADATA
parse_2d-1.0.0.dist-info/WHEEL
parse_2d-1.0.0.dist-info/top_level.txt
parse_2d-1.0.0.dist-info/RECORD
