Metadata-Version: 2.1
Name: parse-2d
Version: 1.0.0
Summary: Tools for parsing two-dimensional programming languages
Home-page: https://github.com/madman-bob/python-parse-2d
Author: Robert Wright
Author-email: madman.bob@hotmail.co.uk
License: MIT
Platform: UNKNOWN
Classifier: License :: OSI Approved :: MIT License
Classifier: Programming Language :: Python :: 3
Classifier: Programming Language :: Python :: 3.6
Classifier: Programming Language :: Python :: 3.7
Classifier: Programming Language :: Python :: 3.8
Requires-Python: >=3.6
Requires-Dist: dataclasses
Requires-Dist: more-properties
Requires-Dist: twine
